{
  "date": "2022-05-31",
  "timezone": "Indian/Mauritius",
  "generated": "2026-02-16T18:06:52.240Z",
  "outageCount": 8,
  "outages": [
    {
      "date": "Le mardi 31 mai 2022 de  09:30:00 à  11:00:00",
      "locality": "16EME MILE",
      "localitySlug": "16eme-mile",
      "streets": "Morc Soobhany 16eme Mile",
      "district": "plainewilhems",
      "from": "2022-05-31T05:30:00.000Z",
      "to": "2022-05-31T07:00:00.000Z",
      "id": "c6596e8bb36ad6596ba5ee386f20c278"
    },
    {
      "date": "Le mardi 31 mai 2022 de  15:00:00 à  16:30:00",
      "locality": "VACOAS",
      "localitySlug": "vacoas",
      "streets": "Tres Bon Vacoas",
      "district": "plainewilhems",
      "from": "2022-05-31T11:00:00.000Z",
      "to": "2022-05-31T12:30:00.000Z",
      "id": "c72646e9dfcf4cf786dbb265b02575d9"
    },
    {
      "date": "Le mardi 31 mai 2022 de  09:00:00 à  14:00:00",
      "locality": "VALLEE DES PRETRES",
      "localitySlug": "vallee-des-pretres",
      "streets": "LES ABONNES HABITANT UPPER VALLEE DES PRETRES DANS LES ENVIRONS DE TABAGIE OREE",
      "district": "portlouis",
      "from": "2022-05-31T05:00:00.000Z",
      "to": "2022-05-31T10:00:00.000Z",
      "id": "4c121e40071b5d3c7cb4ee4453bcad2a"
    },
    {
      "date": "Le mardi 31 mai 2022 de  00:00:00 à  00:00:00",
      "locality": "VALLEE DES PRETRES",
      "localitySlug": "vallee-des-pretres",
      "streets": "Croline Vallee",
      "district": "portlouis",
      "from": "2022-05-30T20:00:00.000Z",
      "to": "2022-05-29T20:00:00.000Z",
      "id": "ef832978aedc09178a601f583dfe45d4"
    },
    {
      "date": "Le mardi 31 mai 2022 de  09:45:00 à  11:00:00",
      "locality": "VALLEE DES PRETRES",
      "localitySlug": "vallee-des-pretres",
      "streets": "Croline Vallee des Pretres",
      "district": "portlouis",
      "from": "2022-05-31T05:45:00.000Z",
      "to": "2022-05-31T07:00:00.000Z",
      "id": "41bd3bfec8cc0af0f38c69f9f022611e"
    },
    {
      "date": "Le mardi 31 mai 2022 de  09:00:00 à  12:00:00",
      "locality": "PETIT RAFFRAY",
      "localitySlug": "petit-raffray",
      "streets": "Petit Raffray",
      "district": "rivieredurempart",
      "from": "2022-05-31T05:00:00.000Z",
      "to": "2022-05-31T08:00:00.000Z",
      "id": "739395df12ebba5632364821b49e8db1"
    },
    {
      "date": "Le mardi 31 mai 2022 de  09:00:00 à  10:30:00",
      "locality": "ESPERANCE TREBUCHET",
      "localitySlug": "esperance-trebuchet",
      "streets": "dans les environs de Social Welfare Centre.",
      "district": "rivieredurempart",
      "from": "2022-05-31T05:00:00.000Z",
      "to": "2022-05-31T06:30:00.000Z",
      "id": "3ea4fcc84b445f953197407166ff0e84"
    },
    {
      "date": "Le mardi 31 mai 2022 de  12:00:00 à  14:00:00",
      "locality": "RODRIGUES",
      "localitySlug": "rodrigues",
      "streets": "Terre Rouge",
      "district": "rodrigues",
      "from": "2022-05-31T08:00:00.000Z",
      "to": "2022-05-31T10:00:00.000Z",
      "id": "3aa75604594ec7a5531c137f1f103ce1"
    }
  ]
}