{
  "date": "2024-03-08",
  "timezone": "Indian/Mauritius",
  "generated": "2026-01-04T08:01:06.021Z",
  "outageCount": 1,
  "outages": [
    {
      "date": "Le vendredi 8 mars 2024 de  16:45:00 à  18:45:00",
      "locality": "TRIOLET",
      "localitySlug": "triolet",
      "streets": "GEETANJALI RD, SEWRAAZ ROAD ET TRIO ROAD.",
      "district": "pamplemousses",
      "from": "2024-03-08T12:45:00.000Z",
      "to": "2024-03-08T14:45:00.000Z",
      "id": "3b344f8012f22f89ad21d1f11416aeed"
    }
  ]
}