{
  "date": "2024-05-14",
  "timezone": "Indian/Mauritius",
  "generated": "2026-02-12T15:14:07.928Z",
  "outageCount": 9,
  "outages": [
    {
      "date": "Le mardi 14 mai 2024 de  09:30:00 à  17:00:00",
      "locality": "POSTE DE FLACQ",
      "localitySlug": "poste-de-flacq",
      "streets": "RTE JARDIN NO:2",
      "district": "flacq",
      "from": "2024-05-14T05:30:00.000Z",
      "to": "2024-05-14T13:00:00.000Z",
      "id": "2be29737089a63dec7ff01b5926111c7"
    },
    {
      "date": "Le mardi 14 mai 2024 de  12:30:00 à  15:30:00",
      "locality": "OLIVIA",
      "localitySlug": "olivia",
      "streets": "Nr Playground,Olivia",
      "district": "flacq",
      "from": "2024-05-14T08:30:00.000Z",
      "to": "2024-05-14T11:30:00.000Z",
      "id": "0512ef458cd1d02502175b1d26249517"
    },
    {
      "date": "Le mardi 14 mai 2024 de  14:15:00 à  16:15:00",
      "locality": "CENTRAL FLACQ",
      "localitySlug": "central-flacq",
      "streets": "EN PARTIE MORC PLAINE DE GERSIGNY.",
      "district": "flacq",
      "from": "2024-05-14T10:15:00.000Z",
      "to": "2024-05-14T12:15:00.000Z",
      "id": "91e52bcfd06c269749a683476deeefbd"
    },
    {
      "date": "Le mardi 14 mai 2024 de  15:00:00 à  16:00:00",
      "locality": "PONT LARDIER",
      "localitySlug": "pont-lardier",
      "streets": "PONT LARDIER EN DIRECTION CENTRE.",
      "district": "flacq",
      "from": "2024-05-14T11:00:00.000Z",
      "to": "2024-05-14T12:00:00.000Z",
      "id": "ff2d6d252142087fb8fcb2bb19df5393"
    },
    {
      "date": "Le mardi 14 mai 2024 de  14:50:00 à  16:20:00",
      "locality": "BAMBOUS VIRIEUX",
      "localitySlug": "bambous-virieux",
      "streets": "EN PARTIE BAMBOUS VIRIEUX, GRAND SABLE, PETIT SABLE, POINTE AUX FEUILLES, QUATRE SOEURS ET DEUX FRERES.",
      "district": "grandport",
      "from": "2024-05-14T10:50:00.000Z",
      "to": "2024-05-14T12:20:00.000Z",
      "id": "573557f54dcf48773fef1fd2ac5b3289"
    },
    {
      "date": "Le mardi 14 mai 2024 de  15:00:00 à  18:00:00",
      "locality": "PETIT CAMP",
      "localitySlug": "petit-camp",
      "streets": "une partie de Petit Camp",
      "district": "plainewilhems",
      "from": "2024-05-14T11:00:00.000Z",
      "to": "2024-05-14T14:00:00.000Z",
      "id": "5288b7c6cb6cfeaaec9212fd0d2e4e4c"
    },
    {
      "date": "Le mardi 14 mai 2024 de  10:00:00 à  13:00:00",
      "locality": "VALLEE PITOT",
      "localitySlug": "vallee-pitot",
      "streets": "CHALET ST,PART OF ALMA ST,EID GAH REGION",
      "district": "portlouis",
      "from": "2024-05-14T06:00:00.000Z",
      "to": "2024-05-14T09:00:00.000Z",
      "id": "459bf981a0a2b67077490a0ecc293a23"
    },
    {
      "date": "Le mardi 14 mai 2024 de  15:00:00 à  17:00:00",
      "locality": "PLAINE VERTE",
      "localitySlug": "plaine-verte",
      "streets": "RUE MAGON EN DIRECTION VALLEE PITOT, RUE MADRAS, RUE CALCUTTA.",
      "district": "portlouis",
      "from": "2024-05-14T11:00:00.000Z",
      "to": "2024-05-14T13:00:00.000Z",
      "id": "f01e1850ea87a995dc851f807d80f8ce"
    },
    {
      "date": "Le mardi 14 mai 2024 de  15:00:00 à  16:30:00",
      "locality": "SAINT ANTOINE",
      "localitySlug": "saint-antoine",
      "streets": "MORC PETIT VILLAGE ST ANTOINE GOODLANDS.",
      "district": "rivieredurempart",
      "from": "2024-05-14T11:00:00.000Z",
      "to": "2024-05-14T12:30:00.000Z",
      "id": "08536e25d146fa8367061eb18ac2864c"
    }
  ]
}