{
  "date": "2025-08-06",
  "timezone": "Indian/Mauritius",
  "generated": "2026-01-20T07:05:47.826Z",
  "outageCount": 8,
  "outages": [
    {
      "date": "Le mercredi 6 août 2025 de  09:00:00 à  17:00:00",
      "locality": "POSTE LAFAYETTE",
      "localitySlug": "poste-lafayette",
      "streets": "Les abonnés de Poste Lafayette sont avisés que la fourniture d’énergie sera interrompue de 09:00 à 17:00 Le Mercredi 06 Aout 2025 en raison des travaux urgents qui seront effectués sur le réseau électrique.",
      "district": "flacq",
      "from": "2025-08-06T05:00:00.000Z",
      "to": "2025-08-06T13:00:00.000Z",
      "id": "47998293debcd17edefda37caeee7e8f"
    },
    {
      "date": "Le mercredi 6 août 2025 de  11:05:00 à  13:30:00",
      "locality": "MORC SAINT ANDRE",
      "localitySlug": "morc-saint-andre",
      "streets": "Kalimaye & Royal Roads",
      "district": "pamplemousses",
      "from": "2025-08-06T07:05:00.000Z",
      "to": "2025-08-06T09:30:00.000Z",
      "id": "b672eaf4db448dfab3b0b84d36c32b82"
    },
    {
      "date": "Le mercredi 6 août 2025 de  13:40:00 à  16:00:00",
      "locality": "TRIOLET",
      "localitySlug": "triolet",
      "streets": "BON AIR ROAD AND SURROUNDINGS",
      "district": "pamplemousses",
      "from": "2025-08-06T09:40:00.000Z",
      "to": "2025-08-06T12:00:00.000Z",
      "id": "e0c0a8b2c9dcdead3197fa0c0d849d02"
    },
    {
      "date": "Le mercredi 6 août 2025 de  10:30:00 à  13:00:00",
      "locality": "BELLE ETOILE",
      "localitySlug": "belle-etoile",
      "streets": "WHOLE REGION",
      "district": "plainewilhems",
      "from": "2025-08-06T06:30:00.000Z",
      "to": "2025-08-06T09:00:00.000Z",
      "id": "39da198daf1b2cbd8c7c8de6eab19d79"
    },
    {
      "date": "Le mercredi 6 août 2025 de  15:30:00 à  17:30:00",
      "locality": "ROSE-HILL",
      "localitySlug": "rose-hill",
      "streets": "Ave Berthaud, Res. Trefles, Assembly Lane, Jeetoo Ave, en partie Stanley et Ave Cretin",
      "district": "plainewilhems",
      "from": "2025-08-06T11:30:00.000Z",
      "to": "2025-08-06T13:30:00.000Z",
      "id": "3e8b6e978e5d60759445b086d58fc0de"
    },
    {
      "date": "Le mercredi 6 août 2025 de  09:00:00 à  16:30:00",
      "locality": "ROCHE TERRE",
      "localitySlug": "roche-terre",
      "streets": "WHOLE AREA OF ROCHE TERRE",
      "district": "rivieredurempart",
      "from": "2025-08-06T05:00:00.000Z",
      "to": "2025-08-06T12:30:00.000Z",
      "id": "461f7296733562533163aada0507dde8"
    },
    {
      "date": "Le mercredi 6 août 2025 de  09:00:00 à  16:30:00",
      "locality": "GRAND GAUBE",
      "localitySlug": "grand-gaube",
      "streets": "WHOLE AREA OF GRAND GAUBE",
      "district": "rivieredurempart",
      "from": "2025-08-06T05:00:00.000Z",
      "to": "2025-08-06T12:30:00.000Z",
      "id": "93d622213579e053a21dbaaac0924454"
    },
    {
      "date": "Le mercredi 6 août 2025 de  16:40:00 à  21:15:00",
      "locality": "RIVIERE DU REMPART",
      "localitySlug": "riviere-du-rempart",
      "streets": "NUNKA ROAD RIVIERE DU REMPART",
      "district": "rivieredurempart",
      "from": "2025-08-06T12:40:00.000Z",
      "to": "2025-08-06T17:15:00.000Z",
      "id": "93f54a3cc778573b4d2a08b5a02e4cd1"
    }
  ]
}