{
  "date": "2026-01-15",
  "timezone": "Indian/Mauritius",
  "generated": "2026-01-09T16:01:08.948Z",
  "outageCount": 1,
  "outages": [
    {
      "date": "Le jeudi 15 janvier 2026 de  09:00:00 à  17:00:00",
      "locality": "ROSE BELLE",
      "localitySlug": "rose-belle",
      "streets": "Rose Belle habitant dans le périmètre et les rues suivantes : Morcellement Haton, VRS Orchidee, Madame Lolo, MITD Rose Belle, Ajanta Road, Capitol Dream Mall, Cité EDC Madame Lolo, La Gare Street, Kulpoo Lane, Railway Road, Mongelard Road et une partie de la Route Royale Rose Belle",
      "district": "grandport",
      "from": "2026-01-15T05:00:00.000Z",
      "to": "2026-01-15T13:00:00.000Z",
      "id": "8564ec42ac53f2b0cb03437b343ead4a"
    }
  ]
}