{
  "date": "2026-05-04",
  "timezone": "Indian/Mauritius",
  "generated": "2026-06-04T15:09:30.668Z",
  "outageCount": 8,
  "outages": [
    {
      "date": "Le lundi 4 mai 2026 de  14:00:00 à  19:00:00",
      "locality": "BAMBOUS",
      "localitySlug": "bambous",
      "streets": "AVENUE DES SOURCES, AVENUE ST SAUVEUR, AVENUE CENTRAL ET LES ENVIRONS.",
      "district": "blackriver",
      "from": "2026-05-04T10:00:00.000Z",
      "to": "2026-05-04T15:00:00.000Z",
      "id": "503aad9e612dee69eaa608492a5a042b"
    },
    {
      "date": "Le lundi 4 mai 2026 de  18:00:00 à  20:00:00",
      "locality": "MOKA",
      "localitySlug": "moka",
      "streets": "Soreze, Moka, St Pierre, Lavenir, Verdun, N Decouvert, Malenga, La Laura, Cote Dor Partly",
      "district": "moka",
      "from": "2026-05-04T14:00:00.000Z",
      "to": "2026-05-04T16:00:00.000Z",
      "id": "20c82180b128f62196596d35ae947b20"
    },
    {
      "date": "Le lundi 4 mai 2026 de  19:00:00 à  00:00:00",
      "locality": "MOKA",
      "localitySlug": "moka",
      "streets": "CAMP SAMI, BOIS CHERIE ROAD AND SURROUNDINGS",
      "district": "moka",
      "from": "2026-05-04T15:00:00.000Z",
      "to": "2026-05-03T20:00:00.000Z",
      "id": "02dadc03f808d4d755b3702df54aa1c7"
    },
    {
      "date": "Le lundi 4 mai 2026 de  14:20:00 à  16:45:00",
      "locality": "ARSENAL",
      "localitySlug": "arsenal",
      "streets": "ROYAL ROAD ARSENAL AND BALACLAVA.",
      "district": "pamplemousses",
      "from": "2026-05-04T10:20:00.000Z",
      "to": "2026-05-04T12:45:00.000Z",
      "id": "9699895e117deb8ca8041578eaafbaf0"
    },
    {
      "date": "Le lundi 4 mai 2026 de  11:25:00 à  15:00:00",
      "locality": "SODNAC",
      "localitySlug": "sodnac",
      "streets": "HILLCREST SODNAC, AVE CARDINAL ET LES ALENTOURS",
      "district": "plainewilhems",
      "from": "2026-05-04T07:25:00.000Z",
      "to": "2026-05-04T11:00:00.000Z",
      "id": "57931135b03c9ff52d8a794500e543e1"
    },
    {
      "date": "Le lundi 4 mai 2026 de  15:30:00 à  16:30:00",
      "locality": "CUREPIPE",
      "localitySlug": "curepipe",
      "streets": "RUE LEES : BUREAU BRINKS, MAURITIUS HOUSING ET MEDICAL HEARING CENTRE.",
      "district": "plainewilhems",
      "from": "2026-05-04T11:30:00.000Z",
      "to": "2026-05-04T12:30:00.000Z",
      "id": "d024a54eb842aa32f177c926896fdaa0"
    },
    {
      "date": "Le lundi 4 mai 2026 de  18:30:00 à  22:45:00",
      "locality": "RIVIERE DU REMPART",
      "localitySlug": "riviere-du-rempart",
      "streets": "BEEJADHUR STREET & SURROUNDINGS",
      "district": "rivieredurempart",
      "from": "2026-05-04T14:30:00.000Z",
      "to": "2026-05-04T18:45:00.000Z",
      "id": "2230f0f1421fb64bde7177f2b3d36257"
    },
    {
      "date": "Le lundi 4 mai 2026 de  15:45:00 à  17:00:00",
      "locality": "CHEMIN GRENIER",
      "localitySlug": "chemin-grenier",
      "streets": "AVE WILLIAM LORKER & SURROUNDINGS",
      "district": "savanne",
      "from": "2026-05-04T11:45:00.000Z",
      "to": "2026-05-04T13:00:00.000Z",
      "id": "d76503c600ddfd4e522d1abd9ffa5b8f"
    }
  ]
}