{"today":[{"date":"Le lundi 7 avril 2025 de  14:00:00 à  17:00:00","locality":"CALEBASSES","streets":"","district":"pamplemousses","from":"2025-04-07T10:00:00.000Z","to":"2025-04-07T13:00:00.000Z","id":"aee8d59065094f30d012e1a20d5787bd"},{"date":"Le lundi 7 avril 2025 de  21:30:00 à  23:30:00","locality":"CHEMIN GRENIER","streets":"CHEMIN GRENIER","district":"savanne","from":"2025-04-07T17:30:00.000Z","to":"2025-04-07T19:30:00.000Z","id":"afea7f4d8982be50194c95e52bac81e3"}],"future":[{"date":"Le jeudi 10 avril 2025 de  08:30:00 à  16:30:00","locality":"RIVIERE NOIRE","streets":"LA JETEE ROAD ET AVENUE COLONEL DEAN","district":"blackriver","from":"2025-04-10T04:30:00.000Z","to":"2025-04-10T12:30:00.000Z","id":"22ed16acbad2055f0258ec1b06da345f"},{"date":"Le mardi 8 avril 2025 de  09:30:00 à  11:00:00","locality":"BELLE MARE","streets":"Village de Belle Mare dans les environs de la Route royale, Ambre Hotel, La Veranda Hotel et La Residence Hotel.","district":"flacq","from":"2025-04-08T05:30:00.000Z","to":"2025-04-08T07:00:00.000Z","id":"9ac1efbbe8d026d1c04a7edcc65eb226"}]}