{"today":[{"date":"Le lundi 27 avril 2026 de  14:15:00 à  16:15:00","locality":"MONT IDA","streets":"MONT IDA","district":"flacq","from":"2026-04-27T10:15:00.000Z","to":"2026-04-27T12:15:00.000Z","id":"815120e8e3d83038fc35f75b9382e79b","outageId":"10ed9363cbe4508d5cb29c230e7719df"},{"date":"Le lundi 27 avril 2026 de  15:00:00 à  18:00:00","locality":"SAINT PIERRE","streets":"Bois Cheri Rd, Riviere Baptiste, Le Pouce, St Pierre Village, Chemin Tafazul et Chantenay Petit Verger","district":"moka","from":"2026-04-27T11:00:00.000Z","to":"2026-04-27T14:00:00.000Z","id":"6abd052f240b067e1527b35b2df9983c","outageId":"013966f7c2ee1250a9f9e62685622361"},{"date":"Le lundi 27 avril 2026 de  10:00:00 à  11:30:00","locality":"CUREPIPE","streets":"ROUTE DEPINAY CUREPIPE","district":"plainewilhems","from":"2026-04-27T06:00:00.000Z","to":"2026-04-27T07:30:00.000Z","id":"be88c100616505e3e56f38092d32fd5e","outageId":"3ecec03762fa489204fddb269b9f32cb"},{"date":"Le lundi 27 avril 2026 de  10:00:00 à  14:00:00","locality":"QUATRE-BORNES","streets":"RUE COSSIGNY/WELLINGTON","district":"plainewilhems","from":"2026-04-27T06:00:00.000Z","to":"2026-04-27T10:00:00.000Z","id":"0359835c4a333ce9fb8b40306d0ea183","outageId":"52e88ab2317fe9752b5657edb3a320ad"},{"date":"Le lundi 27 avril 2026 de  10:00:00 à  12:30:00","locality":"ROSE-HILL","streets":"RUE AMBROSE ROSEHILL","district":"plainewilhems","from":"2026-04-27T06:00:00.000Z","to":"2026-04-27T08:30:00.000Z","id":"34e497f01a2b805c671dbdce0ae04624","outageId":"c2838e244efae46e76e65995579b1b05"},{"date":"Le lundi 27 avril 2026 de  10:45:00 à  12:00:00","locality":"VALLEE DES PRETRES","streets":"CARREAU LALO VALLEE DES PRETRES","district":"portlouis","from":"2026-04-27T06:45:00.000Z","to":"2026-04-27T08:00:00.000Z","id":"c42cb4c28f3d4a875d7109374399cf82","outageId":"fc31ef2a9daf6299d34347ab3f587836"},{"date":"Le lundi 27 avril 2026 de  10:30:00 à  11:30:00","locality":"RIVIERE DU REMPART","streets":"LA CLEMANCE","district":"rivieredurempart","from":"2026-04-27T06:30:00.000Z","to":"2026-04-27T07:30:00.000Z","id":"67ae31ecbd9995410514d4e945276503","outageId":"c0961ca3a8aa631caf97ed120a800d6a"}],"future":[{"date":"Le samedi 2 mai 2026 de  08:30:00 à  14:00:00","locality":"BAMBOUS","streets":"AVE CENTRALE, AVE EAU BONNE, AVE SAINT-SAUVEUR, AVE DES SOURCES, AVE LAVANDERIE ET AVE LA FERME","district":"blackriver","from":"2026-05-02T04:30:00.000Z","to":"2026-05-02T10:00:00.000Z","id":"3157da8711403329b65f894d4f9a53e5","outageId":"900c98c4dd115718853aeeab29d5f1cc"},{"date":"Le mardi 28 avril 2026 de  09:00:00 à  15:00:00","locality":"MAHEBOURG","streets":"Beau Vallon et Mahebourg habitant dans le périmètre et les rues suivantes: Gopeelall Lane, Ramnarain Lane, Impasse Auffray, une partie de (Tombeau Lane, Allée Geude, Gopala Lane, Doolar Lane, Rue du Bamboo, Rue Nyon, Rue Souffleur, Abdool Razack Mohamed Street) et Chemin Grove Industries Beau Vallon","district":"grandport","from":"2026-04-28T05:00:00.000Z","to":"2026-04-28T11:00:00.000Z","id":"afa7ea5f0ad94e73e9fe81ebd665fb17","outageId":"ea90e7268c52accda329753af386d16a"}]}