{"today":[{"date":"Le samedi 17 août 2024 de  08:30:00 à  15:30:00","locality":"NOUVELLE DECOUVERTE","streets":"L’ESCALIER BRANCH RD, RAJABALLY BRANCH RD, FORGET, BUMMAH RD et LES ENVIRONS","district":"moka","from":"2024-08-17T04:30:00.000Z","to":"2024-08-17T11:30:00.000Z","id":"ba41de03e6c5f4ae0f0ab8de5c72a6dc"},{"date":"Le samedi 17 août 2024 de  08:30:00 à  15:30:00","locality":"TERRE ROUGE","streets":"Dans les environs de Winners, Route Royal Terre Rouge, KJW Lane, Dr Manilall Road et Patisserie Shah","district":"pamplemousses","from":"2024-08-17T04:30:00.000Z","to":"2024-08-17T11:30:00.000Z","id":"d5f3d41e333101880648ba7eb3c1ee11"},{"date":"Le samedi 17 août 2024 de  08:30:00 à  15:00:00","locality":"COROMANDEL - R.HILL","streets":"MARE GRAVIER COROMANDEL DOOKHUN LN, RAOUL FOLLEREREAU, BISSAWON BIKOO, DR MOLIERE, EDGAR ADOLPHE et LES ENVIRONS","district":"plainewilhems","from":"2024-08-17T04:30:00.000Z","to":"2024-08-17T11:00:00.000Z","id":"c94d95ff4272f283ad9793e43ab42824"},{"date":"Le samedi 17 août 2024 de  08:30:00 à  15:00:00","locality":"SAINTE CROIX","streets":"LES ABONNES HABITANT RESIDENCE BRIQUETTERIE SAINTE CROIX DANS LES ENVIRONS DES RUES BOIS SAVON, CORSON, ABERCOMBIE, LAVOCAIRE, BOISEE, PAUL, VERONCE, AIGLE ET BRIQUETTERIE","district":"portlouis","from":"2024-08-17T04:30:00.000Z","to":"2024-08-17T11:00:00.000Z","id":"7f8cefba82e39c573d266fb42f395a02"},{"date":"Le samedi 17 août 2024 de  08:30:00 à  15:00:00","locality":"GOODLANDS","streets":"dans les environs de Morc Annath","district":"rivieredurempart","from":"2024-08-17T04:30:00.000Z","to":"2024-08-17T11:00:00.000Z","id":"0c8b18d5e8af0fc234c6e587d56cefa1"},{"date":"Le samedi 17 août 2024 de  09:00:00 à  16:00:00","locality":"RODRIGUES","streets":"CAMP PAINTADE -LA FERME RODRIGUES","district":"rodrigues","from":"2024-08-17T05:00:00.000Z","to":"2024-08-17T12:00:00.000Z","id":"feaa91740696c52990b6fc8a4d27ff1a"}],"future":[{"date":"Le dimanche 18 août 2024 de  08:30:00 à  15:30:00","locality":"SAINT PIERRE","streets":"LAVENIR, MORC FRANGIPANE, MORC BLUEPRINT, MORC L’AVENIR VRS 1, VILLAGE L’AVENIR et LES ENVIRONS","district":"moka","from":"2024-08-18T04:30:00.000Z","to":"2024-08-18T11:30:00.000Z","id":"18d3d5b1063b4e7e30ea308876469c3b"},{"date":"Le dimanche 18 août 2024 de  08:30:00 à  15:30:00","locality":"TERRE ROUGE","streets":"Dans les environs de Route Royal, Poste de Police, Mauritius Telecom, Camp La Boue et une partie de la route St Joseph","district":"pamplemousses","from":"2024-08-18T04:30:00.000Z","to":"2024-08-18T11:30:00.000Z","id":"c738bf0cc8f6bf40f384a6a5c393fd16"},{"date":"Le dimanche 18 août 2024 de  08:30:00 à  16:00:00","locality":"HIGHLANDS","streets":"MORC MTMD NO. 1 ET No. 2","district":"plainewilhems","from":"2024-08-18T04:30:00.000Z","to":"2024-08-18T12:00:00.000Z","id":"c4bc88f609965030ce1983f48ac17e06"},{"date":"Le dimanche 18 août 2024 de  08:00:00 à  17:00:00","locality":"CAMP FOUQUEREAUX","streets":"Reservoir Road, une partie de St Antoine Road, Morc Ramanah, Constantin Road, Purryag Lane, une Partie de Galea Road","district":"plainewilhems","from":"2024-08-18T04:00:00.000Z","to":"2024-08-18T13:00:00.000Z","id":"96a812c6c5c171cbc49e10a2074b8a69"}]}