{
  "slug": "belle-mare",
  "name": "BELLE MARE",
  "district": "flacq",
  "generated": "2026-01-19T16:02:01.447Z",
  "outageCount": 28,
  "firstOutage": "2022-08-07",
  "lastOutage": "2026-01-08",
  "outages": [
    {
      "date": "Le jeudi 8 janvier 2026 de  13:00:00 à  19:00:00",
      "streets": "BELLE MARE, PALMAR",
      "from": "2026-01-08T09:00:00.000Z",
      "to": "2026-01-08T15:00:00.000Z",
      "id": "22f0f67e686c40d8766375761ef58b16"
    },
    {
      "date": "Le dimanche 7 septembre 2025 de  08:45:00 à  16:00:00",
      "streets": "Belle Mare dans le périmètre de Hotel Residence jusqu’au Hotel Ambre.",
      "from": "2025-09-07T04:45:00.000Z",
      "to": "2025-09-07T12:00:00.000Z",
      "id": "b0d93ecdf60e1660d724c7a124573f8c"
    },
    {
      "date": "Le jeudi 31 juillet 2025 de  14:00:00 à  16:30:00",
      "streets": "PART OF BELLE MARE",
      "from": "2025-07-31T10:00:00.000Z",
      "to": "2025-07-31T12:30:00.000Z",
      "id": "728ab627adaa4d857b59ae76b90d5237"
    },
    {
      "date": "Le jeudi 31 juillet 2025 de  12:45:00 à  14:45:00",
      "streets": "Belle Mare",
      "from": "2025-07-31T08:45:00.000Z",
      "to": "2025-07-31T10:45:00.000Z",
      "id": "faf8c6e22b7eb2351f3fbb90ff4c2c2e"
    },
    {
      "date": "Le samedi 12 juillet 2025 de  10:00:00 à  11:00:00",
      "streets": "LAND SETTLEMENT AND SURROUNDINGS",
      "from": "2025-07-12T06:00:00.000Z",
      "to": "2025-07-12T07:00:00.000Z",
      "id": "f381acef936229850b524bed555e93fc"
    },
    {
      "date": "Le mardi 8 juillet 2025 de  15:30:00 à  17:30:00",
      "streets": "SHANTINAGAR TOWARDS LA GROTTE",
      "from": "2025-07-08T11:30:00.000Z",
      "to": "2025-07-08T13:30:00.000Z",
      "id": "cc1a561a4f8b36196362e115240d49ad"
    },
    {
      "date": "Le mardi 8 avril 2025 de  09:30:00 à  11:00:00",
      "streets": "Village de Belle Mare dans les environs de la Route royale, Ambre Hotel, La Veranda Hotel et La Residence Hotel.",
      "from": "2025-04-08T05:30:00.000Z",
      "to": "2025-04-08T07:00:00.000Z",
      "id": "9ac1efbbe8d026d1c04a7edcc65eb226"
    },
    {
      "date": "Le mercredi 19 mars 2025 de  11:30:00 à  13:00:00",
      "streets": "CREMATION RD BELLE MARE",
      "from": "2025-03-19T07:30:00.000Z",
      "to": "2025-03-19T09:00:00.000Z",
      "id": "c77f92041c6b3e9bbbc59064c510b4c8"
    },
    {
      "date": "Le mardi 1 octobre 2024 de  09:00:00 à  12:00:00",
      "streets": "Dans les environs de St Geran Hotel et ave Dodo.",
      "from": "2024-10-01T05:00:00.000Z",
      "to": "2024-10-01T08:00:00.000Z",
      "id": "69b1abfdec337a7e3d3db0b80f1f285e"
    },
    {
      "date": "Le mardi 10 septembre 2024 de  09:00:00 à  16:00:00",
      "streets": "Belle Mare dans les environs de LHotel St Geran et Chemin Dodo.",
      "from": "2024-09-10T05:00:00.000Z",
      "to": "2024-09-10T12:00:00.000Z",
      "id": "a98acba10bfbe39b42327dea662bf0fb"
    },
    {
      "date": "Le lundi 9 septembre 2024 de  09:00:00 à  17:00:00",
      "streets": "Morc constance, LHotel de Saint Geran et ave Dodo",
      "from": "2024-09-09T05:00:00.000Z",
      "to": "2024-09-09T13:00:00.000Z",
      "id": "844c8351e5fca5559b729676e58cc980"
    },
    {
      "date": "Le samedi 31 août 2024 de  08:30:00 à  16:00:00",
      "streets": "Morc Constance",
      "from": "2024-08-31T04:30:00.000Z",
      "to": "2024-08-31T12:00:00.000Z",
      "id": "5e256d27831e9584b6b4502b1b0304a6"
    },
    {
      "date": "Le dimanche 4 août 2024 de  08:30:00 à  17:00:00",
      "streets": "BELLE MARE",
      "from": "2024-08-04T04:30:00.000Z",
      "to": "2024-08-04T13:00:00.000Z",
      "id": "b3667bfb0b04efb154050c57a4e9ad59"
    },
    {
      "date": "Le mercredi 17 juillet 2024 de  08:30:00 à  17:00:00",
      "streets": "Belle Mare, Mare La Chaux et Quatre Cocos dans le perimetre de Camp Rannoo rd, Route Royale, Almanda Ave, Goolaiti Ave et Binda Ln",
      "from": "2024-07-17T04:30:00.000Z",
      "to": "2024-07-17T13:00:00.000Z",
      "id": "9a67bd2d4fdddcc3c3eaeb118f64f591"
    },
    {
      "date": "Le jeudi 9 mai 2024 de  09:00:00 à  15:00:00",
      "streets": "Belle Mare: Land Settlement(squatters), La residence, Veranda, Station De Police, Residence OTF et Residence Thalassa.",
      "from": "2024-05-09T05:00:00.000Z",
      "to": "2024-05-09T11:00:00.000Z",
      "id": "c0622cb7c904b881198da8dc5ed9a5c2"
    },
    {
      "date": "Le mercredi 8 mai 2024 de  11:45:00 à  13:00:00",
      "streets": "Route Cotiere Belle Mare & Palmar",
      "from": "2024-05-08T07:45:00.000Z",
      "to": "2024-05-08T09:00:00.000Z",
      "id": "036f7d826275dadc034b33f2f2cc0b51"
    },
    {
      "date": "Le samedi 27 avril 2024 de  08:30:00 à  17:00:00",
      "streets": "Une partie des Hotels de Belle Mare et Palmar",
      "from": "2024-04-27T04:30:00.000Z",
      "to": "2024-04-27T13:00:00.000Z",
      "id": "fcc7b7470dd96204e435783f1da7824e"
    },
    {
      "date": "Le mercredi 28 février 2024 de  10:00:00 à  11:30:00",
      "streets": "COMPLEX IMAYAM, PART OF PUBLIC BEACH",
      "from": "2024-02-28T06:00:00.000Z",
      "to": "2024-02-28T07:30:00.000Z",
      "id": "0c04b6d3f2b0dadc8ad15a9c7ed6b595"
    },
    {
      "date": "Le dimanche 18 février 2024 de  09:00:00 à  17:00:00",
      "streets": "MARE DU PUIT RD, COASTAL RD, SHANTI NAGAR",
      "from": "2024-02-18T05:00:00.000Z",
      "to": "2024-02-18T13:00:00.000Z",
      "id": "167dcc436d0ec8122af2380d2303a801"
    },
    {
      "date": "Le mercredi 31 janvier 2024 de  09:25:00 à  11:30:00",
      "streets": "BELLE MARE",
      "from": "2024-01-31T05:25:00.000Z",
      "to": "2024-01-31T07:30:00.000Z",
      "id": "01e13dccba794979ed68004a279ed790"
    },
    {
      "date": "Le mardi 23 janvier 2024 de  17:00:00 à  19:00:00",
      "streets": "FROM HOTEL ILE DAMBRE TILL POLICE STATION.",
      "from": "2024-01-23T13:00:00.000Z",
      "to": "2024-01-23T15:00:00.000Z",
      "id": "367f80a22b665b164294fa9f8aef4158"
    },
    {
      "date": "Le dimanche 21 janvier 2024 de  13:00:00 à  15:00:00",
      "streets": "BELLE MARE",
      "from": "2024-01-21T09:00:00.000Z",
      "to": "2024-01-21T11:00:00.000Z",
      "id": "98851b076ffb8334993b965867460652"
    },
    {
      "date": "Le samedi 20 janvier 2024 de  06:00:00 à  11:00:00",
      "streets": "JUGGO LANE BELLE MARE",
      "from": "2024-01-20T02:00:00.000Z",
      "to": "2024-01-20T07:00:00.000Z",
      "id": "5d5d4f4bbe114f64b1e8cd45644ff3ae"
    },
    {
      "date": "Le dimanche 31 décembre 2023 de  04:00:00 à  11:00:00",
      "streets": "BASSIN REQUIN BELLE MARE",
      "from": "2023-12-31T00:00:00.000Z",
      "to": "2023-12-31T07:00:00.000Z",
      "id": "05a729f9a838e2186d2f539a3b808e21"
    },
    {
      "date": "Le dimanche 17 décembre 2023 de  08:30:00 à  17:00:00",
      "streets": "Les abonnes du village de Belle Mare dans les périmètres de Salt of Palmar Hotel, Restaurant Orchid Villa et Sun Tan Hotel",
      "from": "2023-12-17T04:30:00.000Z",
      "to": "2023-12-17T13:00:00.000Z",
      "id": "4941cae3d35fc9b5c1d26434dbbe84d8"
    },
    {
      "date": "Le mercredi 5 juillet 2023 de  10:00:00 à  15:00:00",
      "streets": "BELLE MARE",
      "from": "2023-07-05T06:00:00.000Z",
      "to": "2023-07-05T11:00:00.000Z",
      "id": "59d37e2eca6b0cd4413060ee7b59fb49"
    },
    {
      "date": "Le dimanche 21 août 2022 de  08:00:00 à  16:00:00",
      "streets": "BELLE MARE VILLAGE",
      "from": "2022-08-21T04:00:00.000Z",
      "to": "2022-08-21T12:00:00.000Z",
      "id": "5eed2eda55eaad1085814373b3b0fa10"
    },
    {
      "date": "Le dimanche 7 août 2022 de  08:15:00 à  16:00:00",
      "streets": "Belle-Mare  dans les périmètres de la Station de Police Belle Mare et Hotel Sunrise",
      "from": "2022-08-07T04:15:00.000Z",
      "to": "2022-08-07T12:00:00.000Z",
      "id": "52c1ce73a470acc1ead495f28493be9d"
    }
  ]
}