{
  "slug": "d-epinay",
  "name": "D-EPINAY",
  "district": "pamplemousses",
  "generated": "2026-02-08T15:03:04.147Z",
  "outageCount": 14,
  "firstOutage": "2022-08-01",
  "lastOutage": "2025-09-03",
  "outages": [
    {
      "date": "Le mercredi 3 septembre 2025 de  09:00:00 à  15:00:00",
      "streets": "DÉpinay",
      "from": "2025-09-03T05:00:00.000Z",
      "to": "2025-09-03T11:00:00.000Z",
      "id": "7cf9fcab80604c2ad4e1e1397678fa33"
    },
    {
      "date": "Le dimanche 10 août 2025 de  20:00:00 à  00:30:00",
      "streets": "DEPINAY,ILLOT.PETITE JULIE",
      "from": "2025-08-10T16:00:00.000Z",
      "to": "2025-08-09T20:30:00.000Z",
      "id": "7eb15fa4f2e5d9b0184cca4469005938"
    },
    {
      "date": "Le mercredi 2 avril 2025 de  20:30:00 à  23:00:00",
      "streets": "DEPINAY",
      "from": "2025-04-02T16:30:00.000Z",
      "to": "2025-04-02T19:00:00.000Z",
      "id": "13d40a12a808a943f0ff865178a4074a"
    },
    {
      "date": "Le mercredi 11 décembre 2024 de  12:45:00 à  14:00:00",
      "streets": "JOUVENCE",
      "from": "2024-12-11T08:45:00.000Z",
      "to": "2024-12-11T10:00:00.000Z",
      "id": "4466c63dc2282e51e774739f84b8e592"
    },
    {
      "date": "Le dimanche 27 octobre 2024 de  00:00:00 à  14:00:00",
      "streets": "REGION DEPINAY,MARE DAUSTRALIA,VILLE BAGUE,PETITE JULIE,MOUNT,MONGOUT.",
      "from": "2024-10-26T20:00:00.000Z",
      "to": "2024-10-26T10:00:00.000Z",
      "id": "eab64d130be97601d702c75135eed33f"
    },
    {
      "date": "Le mardi 23 juillet 2024 de  13:00:00 à  15:00:00",
      "streets": "DEPINAY,VILLE BAGUE,PETITE JULIE,CONGOMAH,LE MARIANNE,CERVECOEUR.",
      "from": "2024-07-23T09:00:00.000Z",
      "to": "2024-07-23T11:00:00.000Z",
      "id": "69a2aad6660bee524e00420ac5636438"
    },
    {
      "date": "Le mercredi 19 juin 2024 de  08:30:00 à  15:00:00",
      "streets": "DEPINAY, FAMILY SUPERMARKET & PART OF ILOT",
      "from": "2024-06-19T04:30:00.000Z",
      "to": "2024-06-19T11:00:00.000Z",
      "id": "71e41f1945faee989cade23be2543925"
    },
    {
      "date": "Le vendredi 14 juin 2024 de  10:30:00 à  12:00:00",
      "streets": "ROYAL ROAD AND SURROUNDINGS",
      "from": "2024-06-14T06:30:00.000Z",
      "to": "2024-06-14T08:00:00.000Z",
      "id": "3e74d18987e7b00ecef6036af98e8102"
    },
    {
      "date": "Le mercredi 29 mai 2024 de  08:00:00 à  16:00:00",
      "streets": "LES ABONNES D-EPINAY.",
      "from": "2024-05-29T04:00:00.000Z",
      "to": "2024-05-29T12:00:00.000Z",
      "id": "5a97fa45677a5b3186c3572e8b42e080"
    },
    {
      "date": "Le mercredi 27 mars 2024 de  08:30:00 à  12:00:00",
      "streets": "DEpinay et Congomah",
      "from": "2024-03-27T04:30:00.000Z",
      "to": "2024-03-27T08:00:00.000Z",
      "id": "fddfa9537349d515d9356424b595f746"
    },
    {
      "date": "Le dimanche 4 février 2024 de  09:00:00 à  12:00:00",
      "streets": "VILLE BAGUE, PETITE JULIE, DEPINAY, CONGOMAH, LES MARIANES",
      "from": "2024-02-04T05:00:00.000Z",
      "to": "2024-02-04T08:00:00.000Z",
      "id": "55e7df39b11390e0feb2db01c8e48212"
    },
    {
      "date": "Le dimanche 21 janvier 2024 de  08:00:00 à  11:00:00",
      "streets": "Village Depinay",
      "from": "2024-01-21T04:00:00.000Z",
      "to": "2024-01-21T07:00:00.000Z",
      "id": "d959963e2311bb39caef8d0504e93df9"
    },
    {
      "date": "Le samedi 10 juin 2023 de  09:00:00 à  13:00:00",
      "streets": "ROYAL ROAD DEPINAY NR MAXICLEAN",
      "from": "2023-06-10T05:00:00.000Z",
      "to": "2023-06-10T09:00:00.000Z",
      "id": "ae612adcec1e88015db100e9316ed2b0"
    },
    {
      "date": "Le lundi 1 août 2022 de  15:00:00 à  17:30:00",
      "streets": "LES ABONNES HABITANT DEPINAY",
      "from": "2022-08-01T11:00:00.000Z",
      "to": "2022-08-01T13:30:00.000Z",
      "id": "dcf1e1bafac9a6680fdf0e3dd78e670c"
    }
  ]
}